lunapyutils/__init__.py
lunapyutils-1.0.0.dist-info/METADATA
lunapyutils-1.0.0.dist-info/WHEEL
lunapyutils-1.0.0.dist-info/licenses/LICENSE
lunapyutils-1.0.0.dist-info/RECORD
